debug_calls/__init__.py
debug_calls/decorators.py
debug_calls/py.typed
debug_calls-0.1.0.dist-info/LICENSE
debug_calls-0.1.0.dist-info/METADATA
debug_calls-0.1.0.dist-info/WHEEL
debug_calls-0.1.0.dist-info/top_level.txt
debug_calls-0.1.0.dist-info/RECORD
